yandexdirectpy/__init__.py
yandexdirectpy/core copy.py
yandexdirectpy/core.py
yandexdirectpy/core2.py
yandexdirectpy/decorators.py
yandexdirectpy/exceptions.py
yandexdirectpy/executors.py
yandexdirectpy/loggers.py
yandexdirectpy/settings.py
yandexdirectpy/utils.py
yandexdirectpy-1.1.9.dist-info/METADATA
yandexdirectpy-1.1.9.dist-info/WHEEL
yandexdirectpy-1.1.9.dist-info/top_level.txt
yandexdirectpy-1.1.9.dist-info/RECORD
